README.md
pyproject.toml
ihsan/__init__.py
ihsan/manage.py
ihsan/schema.py
ihsan/sdl/__init__.py
ihsan/sdl/core.py
ihsan/sdl/utils.py
ihsan/utils.py
ihsan-0.0.4.dist-info/entry_points.txt
ihsan-0.0.4.dist-info/LICENSE
ihsan-0.0.4.dist-info/WHEEL
ihsan-0.0.4.dist-info/METADATA
ihsan-0.0.4.dist-info/RECORD
